cst_geometry/__init__.py
cst_geometry/_script.py
cst_geometry/geometry.py
cst_geometry/simple_geometries.py
cst_geometry-0.1.5.dist-info/LICENSE
cst_geometry-0.1.5.dist-info/WHEEL
cst_geometry-0.1.5.dist-info/METADATA
cst_geometry-0.1.5.dist-info/RECORD
