Metadata-Version: 2.1
Name: cst-geometry
Version: 0.1.5
Summary: Package for modeling in CST Microwave studio using python
Home-page: https://github.com/konstantgr/cst_geometry_manager
License: MIT
Author: konstantgr
Author-email: konstantin.grotov@metalab.ifmo.ru
Requires-Python: >=3.7,<4.0
Classifier: License :: OSI Approved :: MIT License
Classifier: Programming Language :: Python :: 3
Classifier: Programming Language :: Python :: 3.7
Classifier: Programming Language :: Python :: 3.8
Classifier: Programming Language :: Python :: 3.9
Project-URL: Repository, https://github.com/konstantgr/cst_geometry_manager
